Metadata-Version: 1.0
Name: frecuency-plot
Version: 0.2
Summary: Percentage bar plot
Home-page: UNKNOWN
Author: Ruben Vilela Freire
Author-email: rubenvf92@gmail.com
License: UNKNOWN
Platform: UNKNOWN
